[
  {
    "title": "Getting Started",
    "list": [
      {
        "title": "Introduction",
        "url":  "/react/introduction"
      },
      {
        "title": "Installation",
        "url":  "/react/installation"
      }
    ]
  },
  {
    "title": "Foundation",
    "list": [
      {
        "title": "Grids",
        "url":  "/react/foundation/grids"
      },
      {
        "title": "Flexbox",
        "url":  "/react/foundation/flexbox"
      }
    ]
  },
  {
    "title": "Components",
    "list": [
      {
        "title": "Button",
        "url":  "/react/component/button"
      },
      {
        "title": "Input",
        "url":  "/react/component/input"
      }
    ]
  }
]